aws_xray_sdk/__init__.py
aws_xray_sdk/sdk_config.py
aws_xray_sdk/version.py
aws_xray_sdk/core/__init__.py
aws_xray_sdk/core/async_context.py
aws_xray_sdk/core/async_recorder.py
aws_xray_sdk/core/context.py
aws_xray_sdk/core/daemon_config.py
aws_xray_sdk/core/lambda_launcher.py
aws_xray_sdk/core/patcher.py
aws_xray_sdk/core/recorder.py
aws_xray_sdk/core/emitters/__init__.py
aws_xray_sdk/core/emitters/udp_emitter.py
aws_xray_sdk/core/exceptions/__init__.py
aws_xray_sdk/core/exceptions/exceptions.py
aws_xray_sdk/core/models/__init__.py
aws_xray_sdk/core/models/default_dynamic_naming.py
aws_xray_sdk/core/models/dummy_entities.py
aws_xray_sdk/core/models/entity.py
aws_xray_sdk/core/models/facade_segment.py
aws_xray_sdk/core/models/http.py
aws_xray_sdk/core/models/noop_traceid.py
aws_xray_sdk/core/models/segment.py
aws_xray_sdk/core/models/subsegment.py
aws_xray_sdk/core/models/throwable.py
aws_xray_sdk/core/models/trace_header.py
aws_xray_sdk/core/models/traceid.py
aws_xray_sdk/core/plugins/__init__.py
aws_xray_sdk/core/plugins/ec2_plugin.py
aws_xray_sdk/core/plugins/ecs_plugin.py
aws_xray_sdk/core/plugins/elasticbeanstalk_plugin.py
aws_xray_sdk/core/plugins/utils.py
aws_xray_sdk/core/sampling/__init__.py
aws_xray_sdk/core/sampling/connector.py
aws_xray_sdk/core/sampling/reservoir.py
aws_xray_sdk/core/sampling/rule_cache.py
aws_xray_sdk/core/sampling/rule_poller.py
aws_xray_sdk/core/sampling/sampler.py
aws_xray_sdk/core/sampling/sampling_rule.py
aws_xray_sdk/core/sampling/target_poller.py
aws_xray_sdk/core/sampling/local/__init__.py
aws_xray_sdk/core/sampling/local/reservoir.py
aws_xray_sdk/core/sampling/local/sampler.py
aws_xray_sdk/core/sampling/local/sampling_rule.json
aws_xray_sdk/core/sampling/local/sampling_rule.py
aws_xray_sdk/core/streaming/__init__.py
aws_xray_sdk/core/streaming/default_streaming.py
aws_xray_sdk/core/utils/__init__.py
aws_xray_sdk/core/utils/atomic_counter.py
aws_xray_sdk/core/utils/compat.py
aws_xray_sdk/core/utils/conversion.py
aws_xray_sdk-2.13.1.dist-info/LICENSE
aws_xray_sdk-2.13.1.dist-info/METADATA
aws_xray_sdk-2.13.1.dist-info/NOTICE
aws_xray_sdk-2.13.1.dist-info/WHEEL
aws_xray_sdk-2.13.1.dist-info/top_level.txt
aws_xray_sdk-2.13.1.dist-info/RECORD
