Metadata-Version: 2.1
Name: aws-xray-sdk
Version: 2.13.1
Summary: The AWS X-Ray SDK for Python (the SDK) enables Python developers to record and emit information from within their applications to the AWS X-Ray service.
Home-page: https://github.com/aws/aws-xray-sdk-python
Author: Amazon Web Services
License: Apache License 2.0
Keywords: aws xray sdk
Classifier: Development Status :: 5 - Production/Stable
Classifier: Intended Audience :: Developers
Classifier: Natural Language :: English
Classifier: License :: OSI Approved :: Apache Software License
Classifier: Programming Language :: Python
Classifier: Programming Language :: Python :: 3
Classifier: Programming Language :: Python :: 3.7
Classifier: Programming Language :: Python :: 3.8
Classifier: Programming Language :: Python :: 3.9
Classifier: Programming Language :: Python :: 3.10
Classifier: Programming Language :: Python :: 3.11
Requires-Python: >=3.7
License-File: LICENSE
License-File: NOTICE
Requires-Dist: wrapt
Requires-Dist: botocore>=1.11.3
